edugrid/__init__.py
edugrid/utils.py
edugrid/algorithms/__init__.py
edugrid/algorithms/dynamic_programming.py
edugrid/algorithms/policy.py
edugrid/envs/__init__.py
edugrid/envs/cells.py
edugrid/envs/grids.py
edugrid/visualization/__init__.py
edugrid/visualization/dynamic_programming.py
edugrid-0.0.2.dist-info/licenses/LICENSE
edugrid-0.0.2.dist-info/METADATA
edugrid-0.0.2.dist-info/WHEEL
edugrid-0.0.2.dist-info/top_level.txt
edugrid-0.0.2.dist-info/RECORD
