Metadata-Version: 2.4
Name: edugrid
Version: 0.0.2
Summary: A Gymnasium grid environment for educational purposes
Author: philsteg
License-Expression: MIT
Project-URL: Source, https://github.com/philsteg/edugrid
Classifier: Programming Language :: Python :: 3
Classifier: Operating System :: OS Independent
Requires-Python: >=3.10
License-File: LICENSE
Requires-Dist: numpy
Requires-Dist: gymnasium
Requires-Dist: matplotlib
Requires-Dist: pygame
Provides-Extra: dev
Requires-Dist: black; extra == "dev"
Requires-Dist: pytest; extra == "dev"
Dynamic: license-file
